{
  "/page": "app/page.js",
  "/(server)/api/(public)/get-all-users/route": "app/(server)/api/(public)/get-all-users/route.js",
  "/(server)/api/(public)/get-all-posts/route": "app/(server)/api/(public)/get-all-posts/route.js",
  "/(server)/api/(user)/get-user-profile/route": "app/(server)/api/(user)/get-user-profile/route.js",
  "/(pages)/(user)/login/page": "app/(pages)/(user)/login/page.js",
  "/(server)/api/(user)/login/route": "app/(server)/api/(user)/login/route.js",
  "/(pages)/(public)/search-users/page": "app/(pages)/(public)/search-users/page.js",
  "/(pages)/(user)/create-post/page": "app/(pages)/(user)/create-post/page.js",
  "/(pages)/(public)/[username]/page": "app/(pages)/(public)/[username]/page.js",
  "/(pages)/(user)/profile/page": "app/(pages)/(user)/profile/page.js"
}